{
  "jobName" : "job_1590936055167_0342",
  "paths" : [ "hdfs://nodemaster:9000/tmp/hive/hadoop/432aef21-7c7f-4d92-9d79-998eff6b5bb0/hive_2020-05-31_18-36-15_873_9179900328993344917-1/-mr-10006" ],
  "locations" : [ "node4" ],
  "jobDataPaths" : [ {
    "path" : "hdfs://nodemaster:9000/tmp/hive/hadoop/432aef21-7c7f-4d92-9d79-998eff6b5bb0/hive_2020-05-31_18-36-15_873_9179900328993344917-1/-mr-10006",
    "filesList" : [ {
      "file" : "HdfsLocatedFileStatus{path=hdfs://nodemaster:9000/tmp/hive/hadoop/432aef21-7c7f-4d92-9d79-998eff6b5bb0/hive_2020-05-31_18-36-15_873_9179900328993344917-1/-mr-10006/000000_0; isDirectory=false; length=963; replication=3; blocksize=134217728; modification_time=1590950264847; access_time=1590950264784; owner=hadoop; group=supergroup; permission=rw-r--r--; isSymlink=false; hasAcl=false; isEncrypted=false; isErasureCoded=false}",
      "blockList" : [ {
        "blockId" : 0,
        "replicaList" : [ {
          "replicaId" : 1,
          "location" : "172.18.0.7:9866",
          "storageId" : "DS-d3d5cb07-f227-4d36-b35b-04035e75c640",
          "storageType" : "DISK",
          "topologyPath" : "/default-rack/172.18.0.7:9866"
        }, {
          "replicaId" : 2,
          "location" : "172.18.0.4:9866",
          "storageId" : "DS-dc295ce4-5227-4dc6-a126-788dc18c66b3",
          "storageType" : "DISK",
          "topologyPath" : "/default-rack/172.18.0.4:9866"
        }, {
          "replicaId" : 3,
          "location" : "172.18.0.5:9866",
          "storageId" : "DS-1f4615cf-20f0-492b-9d33-f531098cd198",
          "storageType" : "DISK",
          "topologyPath" : "/default-rack/172.18.0.5:9866"
        } ]
      } ]
    } ]
  } ]
}