{
  "jobName" : "job_1593115633826_0254",
  "paths" : [ "hdfs://nodemaster:9000/tmp/hive/hadoop/57a2c05e-1a1b-4c5b-beaa-d266fd081e0d/hive_2020-06-25_23-08-47_959_52170206785042860-1/-mr-10005" ],
  "locations" : [ "node4" ],
  "jobDataPaths" : [ {
    "path" : "hdfs://nodemaster:9000/tmp/hive/hadoop/57a2c05e-1a1b-4c5b-beaa-d266fd081e0d/hive_2020-06-25_23-08-47_959_52170206785042860-1/-mr-10005",
    "filesList" : [ {
      "file" : "HdfsLocatedFileStatus{path=hdfs://nodemaster:9000/tmp/hive/hadoop/57a2c05e-1a1b-4c5b-beaa-d266fd081e0d/hive_2020-06-25_23-08-47_959_52170206785042860-1/-mr-10005/000000_0; isDirectory=false; length=32568469; replication=3; blocksize=134217728; modification_time=1593126688354; access_time=1593126687742; owner=hadoop; group=supergroup; permission=rw-r--r--; isSymlink=false; hasAcl=false; isEncrypted=false; isErasureCoded=false}",
      "blockList" : [ {
        "blockId" : 0,
        "replicaList" : [ {
          "replicaId" : 1,
          "location" : "172.18.0.12:9866",
          "storageId" : "DS-d4f5f58a-aa85-428a-a155-ee1f4876f03e",
          "storageType" : "DISK",
          "topologyPath" : "/default-rack/172.18.0.12:9866"
        }, {
          "replicaId" : 2,
          "location" : "172.18.0.5:9866",
          "storageId" : "DS-549d54c8-ddaa-479a-a1c5-7761e6926c22",
          "storageType" : "DISK",
          "topologyPath" : "/default-rack/172.18.0.5:9866"
        }, {
          "replicaId" : 3,
          "location" : "172.18.0.7:9866",
          "storageId" : "DS-59b638d8-2e96-4a0b-b1f4-27e72579b7c8",
          "storageType" : "DISK",
          "topologyPath" : "/default-rack/172.18.0.7:9866"
        } ]
      } ]
    } ]
  } ]
}