{
  "jobName" : "job_1591625479252_0414",
  "paths" : [ "hdfs://nodemaster:9000/user/hive/warehouse/supplier" ],
  "locations" : [ "node11" ],
  "jobDataPaths" : [ {
    "path" : "hdfs://nodemaster:9000/user/hive/warehouse/supplier",
    "filesList" : [ {
      "file" : "HdfsLocatedFileStatus{path=hdfs://nodemaster:9000/user/hive/warehouse/supplier/supplier.tbl; isDirectory=false; length=7088217; replication=3; blocksize=134217728; modification_time=1591625733009; access_time=1591641962995; owner=hadoop; group=supergroup; permission=rw-r--r--; isSymlink=false; hasAcl=false; isEncrypted=false; isErasureCoded=false}",
      "blockList" : [ {
        "blockId" : 0,
        "replicaList" : [ {
          "replicaId" : 1,
          "location" : "172.18.0.7:9866",
          "storageId" : "DS-1e0b1d55-2950-4c23-97ef-b92b12318a29",
          "storageType" : "DISK",
          "topologyPath" : "/default-rack/172.18.0.7:9866"
        }, {
          "replicaId" : 2,
          "location" : "172.18.0.12:9866",
          "storageId" : "DS-53bfee63-0a39-405e-a0cd-61dc3386efab",
          "storageType" : "DISK",
          "topologyPath" : "/default-rack/172.18.0.12:9866"
        }, {
          "replicaId" : 3,
          "location" : "172.18.0.3:9866",
          "storageId" : "DS-d1ae78e9-6da3-4bcf-b901-26aa528ee457",
          "storageType" : "DISK",
          "topologyPath" : "/default-rack/172.18.0.3:9866"
        } ]
      } ]
    } ]
  } ]
}