{
  "jobName" : "job_1591450261235_0334",
  "paths" : [ "hdfs://nodemaster:9000/tmp/hive/hadoop/bbeee7fc-0037-4c85-8bb8-cbcc083d0e90/hive_2020-06-06_17-23-20_437_4953875402164496739-1/-mr-10006" ],
  "locations" : [ "node4" ],
  "jobDataPaths" : [ {
    "path" : "hdfs://nodemaster:9000/tmp/hive/hadoop/bbeee7fc-0037-4c85-8bb8-cbcc083d0e90/hive_2020-06-06_17-23-20_437_4953875402164496739-1/-mr-10006",
    "filesList" : [ {
      "file" : "HdfsLocatedFileStatus{path=hdfs://nodemaster:9000/tmp/hive/hadoop/bbeee7fc-0037-4c85-8bb8-cbcc083d0e90/hive_2020-06-06_17-23-20_437_4953875402164496739-1/-mr-10006/000000_0; isDirectory=false; length=963; replication=3; blocksize=134217728; modification_time=1591464291941; access_time=1591464291877; owner=hadoop; group=supergroup; permission=rw-r--r--; isSymlink=false; hasAcl=false; isEncrypted=false; isErasureCoded=false}",
      "blockList" : [ {
        "blockId" : 0,
        "replicaList" : [ {
          "replicaId" : 1,
          "location" : "172.18.0.5:9866",
          "storageId" : "DS-f136b6a9-8cf0-41e8-9246-e940f750f3ef",
          "storageType" : "DISK",
          "topologyPath" : "/default-rack/172.18.0.5:9866"
        }, {
          "replicaId" : 2,
          "location" : "172.18.0.8:9866",
          "storageId" : "DS-c186c209-35a5-4cac-a1e4-a39f0ffd86ee",
          "storageType" : "DISK",
          "topologyPath" : "/default-rack/172.18.0.8:9866"
        }, {
          "replicaId" : 3,
          "location" : "172.18.0.4:9866",
          "storageId" : "DS-a5c5876e-705f-420a-8c3c-f80de9e3624d",
          "storageType" : "DISK",
          "topologyPath" : "/default-rack/172.18.0.4:9866"
        } ]
      } ]
    } ]
  } ]
}